{
	"id": "mode_event",
	"name": {
		"en": "Event mode",
		"nl": "Eventmodus"
	},
	"images": {
		"large": "drivers/mode_event/assets/images/large.png",
		"small": "drivers/mode_event/assets/images/small.png"
	},
	"class": "other",
	"capabilities": ["onoff"],
	"pair": [
		{
			"id": "list_event",
			"template": "list_devices",
			"navigation": {
				"next": "add_event"
			}
		}, {
			"id": "add_event",
			"template": "add_devices"
		}
	],
	"mobile": {
		"components": [
			{
				"id": "icon",
				"capabilities": ["onoff"]
			}, {
				"id": "toggle",
				"capabilities": ["onoff"]
			}
		]
	}
}